Workbook

Sheet Supuestos
A1: SUPUESTOS — todo lo que puedes cambiar está en amarillo
A3: SERVICIOS Y PRECIOS
A4: Servicio | B4: PVP | C4: Coste unit. | D4: Margen
A5: Web esencial | B5: 1200 | C5: 150 | D5: =IF(B5=0,"",(B5-C5)/B5) | H5: Las cuotas son precio POR MES. Precios revisados con el mapa competitivo de León: mantenimiento 80 EUR (mercado 50-150) y web profesional 2.900 (un competidor local publica 2.500 en tienda online).
A6: Web profesional / e-commerce | B6: 2900 | C6: 600 | D6: =IF(B6=0,"",(B6-C6)/B6)
A7: Identidad visual y diseño gráfico | B7: 950 | C7: 60 | D7: =IF(B7=0,"",(B7-C7)/B7)
A8: Mantenimiento (cuota mensual) | B8: 80 | C8: 15 | D8: =IF(B8=0,"",(B8-C8)/B8)
A9: SEO local (cuota mensual) | B9: 250 | C9: 40 | D9: =IF(B9=0,"",(B9-C9)/B9)
A11: UNIDADES DEL AÑO 1, POR ESCENARIO
A12: Servicio | B12: Pesimista | C12: Previsto | D12: Optimista
A13: Web esencial | B13: 6 | C13: 10 | D13: 14 | H13: El escenario PESIMISTA es el que importa: si con él aguantas, el plan es robusto. El previsto son las 17 ventas del plan de negocio.
A14: Web profesional / e-commerce | B14: 1 | C14: 2 | D14: 3
A15: Identidad visual y diseño gráfico | B15: 3 | C15: 5 | D15: 8
A16: Altas nuevas de mantenimiento al mes | B16: 0.85 | C16: 1.45 | D16: 2.1
A17: Altas nuevas de SEO local al mes | B17: 0.12 | C17: 0.25 | D17: 0.45
A19: ESCENARIO ACTIVO | B19: Previsto | C19: =IF(B19="Pesimista",2,IF(B19="Optimista",4,3)) | H19: Escribe aquí: Pesimista, Previsto u Optimista.
A21: GASTOS FIJOS MENSUALES
A22: Suscripciones (Claude Pro, Adobe, SEO, hosting) | B22: 119
A23: Publicidad y marketing | B23: 125
A24: Cuota de autónomos (tarifa plana) | B24: 80
A25: Asesoría | B25: 65
A26: Desplazamientos | B26: 50
A27: Suministros (ver nota: NO es salida de caja) | B27: 0 | H27: Los suministros de casa (luz, agua, internet) los pagas tengas negocio o no: son DEDUCCIÓN fiscal, no una salida de caja nueva. Por eso van a 0 aquí, aunque sí cuenten como gasto en el plan de negocio.
A28: Material de oficina | B28: 40
A29: Varios | B29: 20
A30: TOTAL GASTOS FIJOS AL MES | B30: =SUM(B22:B29)
A31: Seguro de RC profesional (pago único, mes 1) | B31: 250
A33: CAJA, COBROS E IMPUESTOS
A34: Caja inicial disponible | B34: 179 | H34: Lo que tienes el día 1. Es el número más importante de esta hoja.
A35: % de anticipo al firmar | B35: 0.5 | H35: El resto se cobra al entregar, un mes después.
A36: Retención de IRPF en factura | B36: 0.07 | H36: 7% si te das de alta en epígrafe PROFESIONAL (Secc. 2ª). Pon 0% si es empresarial.
A37: IVA | B37: 0.21 | H37: Tipo general. No es tuyo: lo devuelves cada trimestre.
A38: % de impagos previsto | B38: 0.03 | H38: Ventas que nunca llegas a cobrar. Un 3% es prudente en B2B pequeño.
A39: Baja mensual de clientes recurrentes | B39: 0.01 | H39: Churn. Un 1% al mes es un 12% al año, que es lo normal.
A40: Tu retirada mensual | B40: 0 | H40: Déjalo en 0 los primeros meses. Súbelo cuando la caja aguante.
A43: REPARTO DE LAS VENTAS A LO LARGO DEL AÑO
A44: (rampa de arranque + agosto y diciembre flojos)
B45: M1 | C45: M2 | D45: M3 | E45: M4 | F45: M5 | G45: M6 | H45: M7 | I45: M8 | J45: M9 | K45: M10 | L45: M11 | M45: M12 | N45: SUMA
B46: 0 | C46: 0.04 | D46: 0.07 | E46: 0.09 | F46: 0.11 | G46: 0.11 | H46: 0.1 | I46: 0.03 | J46: 0.11 | K46: 0.13 | L46: 0.13 | M46: 0.08 | N46: =SUM(B46:M46)
B47: =IF(ROUND(N46,4)<>1,"Los pesos deben sumar 100%","Suma 100% correcta")

Sheet Rampa mensual
A1: RAMPA MENSUAL DE TESORERÍA — el año 1, mes a mes
B3: Mes 1 | C3: Mes 2 | D3: Mes 3 | E3: Mes 4 | F3: Mes 5 | G3: Mes 6 | H3: Mes 7 | I3: Mes 8 | J3: Mes 9 | K3: Mes 10 | L3: Mes 11 | M3: Mes 12 | N3: AÑO 1
A4: VENTAS (sin IVA)
A5: Web esencial | B5: =INDEX(Supuestos!$B$13:$D$13,Supuestos!$C$19-1)*Supuestos!B$46*Supuestos!$B$5 | C5: =INDEX(Supuestos!$B$13:$D$13,Supuestos!$C$19-1)*Supuestos!C$46*Supuestos!$B$5 | D5: =INDEX(Supuestos!$B$13:$D$13,Supuestos!$C$19-1)*Supuestos!D$46*Supuestos!$B$5 | E5: =INDEX(Supuestos!$B$13:$D$13,Supuestos!$C$19-1)*Supuestos!E$46*Supuestos!$B$5 | F5: =INDEX(Supuestos!$B$13:$D$13,Supuestos!$C$19-1)*Supuestos!F$46*Supuestos!$B$5 | G5: =INDEX(Supuestos!$B$13:$D$13,Supuestos!$C$19-1)*Supuestos!G$46*Supuestos!$B$5 | H5: =INDEX(Supuestos!$B$13:$D$13,Supuestos!$C$19-1)*Supuestos!H$46*Supuestos!$B$5 | I5: =INDEX(Supuestos!$B$13:$D$13,Supuestos!$C$19-1)*Supuestos!I$46*Supuestos!$B$5 | ... M5: =INDEX(Supuestos!$B$13:$D$13,Supuestos!$C$19-1)*Supuestos!M$46*Supuestos!$B$5 | N5: =SUM(B5:M5)
A6: Web profesional / e-commerce | B6: =INDEX(Supuestos!$B$14:$D$14,Supuestos!$C$19-1)*Supuestos!B$46*Supuestos!$B$6 | C6: =INDEX(Supuestos!$B$14:$D$14,Supuestos!$C$19-1)*Supuestos!C$46*Supuestos!$B$6 | D6: =INDEX(Supuestos!$B$14:$D$14,Supuestos!$C$19-1)*Supuestos!D$46*Supuestos!$B$6 | E6: =INDEX(Supuestos!$B$14:$D$14,Supuestos!$C$19-1)*Supuestos!E$46*Supuestos!$B$6 | F6: =INDEX(Supuestos!$B$14:$D$14,Supuestos!$C$19-1)*Supuestos!F$46*Supuestos!$B$6 | G6: =INDEX(Supuestos!$B$14:$D$14,Supuestos!$C$19-1)*Supuestos!G$46*Supuestos!$B$6 | H6: =INDEX(Supuestos!$B$14:$D$14,Supuestos!$C$19-1)*Supuestos!H$46*Supuestos!$B$6 | I6: =INDEX(Supuestos!$B$14:$D$14,Supuestos!$C$19-1)*Supuestos!I$46*Supuestos!$B$6 | ... M6: =INDEX(Supuestos!$B$14:$D$14,Supuestos!$C$19-1)*Supuestos!M$46*Supuestos!$B$6 | N6: =SUM(B6:M6)
A7: Identidad visual y diseño gráfico | B7: =INDEX(Supuestos!$B$15:$D$15,Supuestos!$C$19-1)*Supuestos!B$46*Supuestos!$B$7 | C7: =INDEX(Supuestos!$B$15:$D$15,Supuestos!$C$19-1)*Supuestos!C$46*Supuestos!$B$7 | D7: =INDEX(Supuestos!$B$15:$D$15,Supuestos!$C$19-1)*Supuestos!D$46*Supuestos!$B$7 | E7: =INDEX(Supuestos!$B$15:$D$15,Supuestos!$C$19-1)*Supuestos!E$46*Supuestos!$B$7 | F7: =INDEX(Supuestos!$B$15:$D$15,Supuestos!$C$19-1)*Supuestos!F$46*Supuestos!$B$7 | G7: =INDEX(Supuestos!$B$15:$D$15,Supuestos!$C$19-1)*Supuestos!G$46*Supuestos!$B$7 | H7: =INDEX(Supuestos!$B$15:$D$15,Supuestos!$C$19-1)*Supuestos!H$46*Supuestos!$B$7 | I7: =INDEX(Supuestos!$B$15:$D$15,Supuestos!$C$19-1)*Supuestos!I$46*Supuestos!$B$7 | ... M7: =INDEX(Supuestos!$B$15:$D$15,Supuestos!$C$19-1)*Supuestos!M$46*Supuestos!$B$7 | N7: =SUM(B7:M7)
A8: Mantenimiento (cartera acumulada) | B8: ='Cartera recurrente'!B7*Supuestos!$B$8 | C8: ='Cartera recurrente'!C7*Supuestos!$B$8 | D8: ='Cartera recurrente'!D7*Supuestos!$B$8 | E8: ='Cartera recurrente'!E7*Supuestos!$B$8 | F8: ='Cartera recurrente'!F7*Supuestos!$B$8 | G8: ='Cartera recurrente'!G7*Supuestos!$B$8 | H8: ='Cartera recurrente'!H7*Supuestos!$B$8 | I8: ='Cartera recurrente'!I7*Supuestos!$B$8 | ... M8: ='Cartera recurrente'!M7*Supuestos!$B$8 | N8: =SUM(B8:M8)
A9: SEO local (cartera acumulada) | B9: ='Cartera recurrente'!B13*Supuestos!$B$9 | C9: ='Cartera recurrente'!C13*Supuestos!$B$9 | D9: ='Cartera recurrente'!D13*Supuestos!$B$9 | E9: ='Cartera recurrente'!E13*Supuestos!$B$9 | F9: ='Cartera recurrente'!F13*Supuestos!$B$9 | G9: ='Cartera recurrente'!G13*Supuestos!$B$9 | H9: ='Cartera recurrente'!H13*Supuestos!$B$9 | I9: ='Cartera recurrente'!I13*Supuestos!$B$9 | ... M9: ='Cartera recurrente'!M13*Supuestos!$B$9 | N9: =SUM(B9:M9)
A10: TOTAL VENTAS | B10: =SUM(B5:B9) | C10: =SUM(C5:C9) | D10: =SUM(D5:D9) | E10: =SUM(E5:E9) | F10: =SUM(F5:F9) | G10: =SUM(G5:G9) | H10: =SUM(H5:H9) | I10: =SUM(I5:I9) | ... M10: =SUM(M5:M9) | N10: =SUM(B10:M10)
A12: COBROS (lo que entra de verdad en el banco)
A13: Proyectos: anticipo al firmar | B13: =SUM(B5:B7)*Supuestos!$B$35 | C13: =SUM(C5:C7)*Supuestos!$B$35 | D13: =SUM(D5:D7)*Supuestos!$B$35 | E13: =SUM(E5:E7)*Supuestos!$B$35 | F13: =SUM(F5:F7)*Supuestos!$B$35 | G13: =SUM(G5:G7)*Supuestos!$B$35 | H13: =SUM(H5:H7)*Supuestos!$B$35 | I13: =SUM(I5:I7)*Supuestos!$B$35 | ... M13: =SUM(M5:M7)*Supuestos!$B$35 | N13: =SUM(B13:M13)
A14: Proyectos: resto al entregar (mes siguiente) | B14: =0 | C14: =SUM(B5:B7)*(1-Supuestos!$B$35) | D14: =SUM(C5:C7)*(1-Supuestos!$B$35) | E14: =SUM(D5:D7)*(1-Supuestos!$B$35) | F14: =SUM(E5:E7)*(1-Supuestos!$B$35) | G14: =SUM(F5:F7)*(1-Supuestos!$B$35) | H14: =SUM(G5:G7)*(1-Supuestos!$B$35) | I14: =SUM(H5:H7)*(1-Supuestos!$B$35) | J14: =SUM(I5:I7)*(1-Supuestos!$B$35) | ... M14: =SUM(L5:L7)*(1-Supuestos!$B$35) | N14: =SUM(B14:M14)
A15: Cuotas recurrentes (domiciliadas) | B15: =SUM(B8:B9) | C15: =SUM(C8:C9) | D15: =SUM(D8:D9) | E15: =SUM(E8:E9) | F15: =SUM(F8:F9) | G15: =SUM(G8:G9) | H15: =SUM(H8:H9) | I15: =SUM(I8:I9) | ... M15: =SUM(M8:M9) | N15: =SUM(B15:M15)
A16: Menos impagos | B16: =-SUM(B13:B15)*Supuestos!$B$38 | C16: =-SUM(C13:C15)*Supuestos!$B$38 | D16: =-SUM(D13:D15)*Supuestos!$B$38 | E16: =-SUM(E13:E15)*Supuestos!$B$38 | F16: =-SUM(F13:F15)*Supuestos!$B$38 | G16: =-SUM(G13:G15)*Supuestos!$B$38 | H16: =-SUM(H13:H15)*Supuestos!$B$38 | I16: =-SUM(I13:I15)*Supuestos!$B$38 | ... M16: =-SUM(M13:M15)*Supuestos!$B$38 | N16: =SUM(B16:M16)
A17: IVA repercutido cobrado | B17: =SUM(B13:B16)*Supuestos!$B$37 | C17: =SUM(C13:C16)*Supuestos!$B$37 | D17: =SUM(D13:D16)*Supuestos!$B$37 | E17: =SUM(E13:E16)*Supuestos!$B$37 | F17: =SUM(F13:F16)*Supuestos!$B$37 | G17: =SUM(G13:G16)*Supuestos!$B$37 | H17: =SUM(H13:H16)*Supuestos!$B$37 | I17: =SUM(I13:I16)*Supuestos!$B$37 | ... M17: =SUM(M13:M16)*Supuestos!$B$37 | N17: =SUM(B17:M17)
A18: Menos retención de IRPF del cliente | B18: =-SUM(B13:B14)*Supuestos!$B$36 | C18: =-SUM(C13:C14)*Supuestos!$B$36 | D18: =-SUM(D13:D14)*Supuestos!$B$36 | E18: =-SUM(E13:E14)*Supuestos!$B$36 | F18: =-SUM(F13:F14)*Supuestos!$B$36 | G18: =-SUM(G13:G14)*Supuestos!$B$36 | H18: =-SUM(H13:H14)*Supuestos!$B$36 | I18: =-SUM(I13:I14)*Supuestos!$B$36 | ... M18: =-SUM(M13:M14)*Supuestos!$B$36 | N18: =SUM(B18:M18)
A19: TOTAL COBROS | B19: =SUM(B13:B18) | C19: =SUM(C13:C18) | D19: =SUM(D13:D18) | E19: =SUM(E13:E18) | F19: =SUM(F13:F18) | G19: =SUM(G13:G18) | H19: =SUM(H13:H18) | I19: =SUM(I13:I18) | ... M19: =SUM(M13:M18) | N19: =SUM(B19:M19)
A21: PAGOS
A22: Coste de ventas (proveedores y freelances) | B22: =-(INDEX(Supuestos!$B$13:$D$13,Supuestos!$C$19-1)*Supuestos!B$46*Supuestos!$C$5+INDEX(Supuestos!$B$14:$D$14,Supuestos!$C$19-1)*Supuestos!B$46*Supuestos!$C$6+INDEX(Supuestos!$B$15:$D$15,Supuestos!$C$19-1)*Supuestos!B$46*Supuestos!$C$7+'Cartera recurrente'!B7*Supuestos!$C$8+'Cartera recurrente'!B13*Supuestos!$C$9)*(1+Supuestos!$B$37) | C22: =-(INDEX(Supuestos!$B$13:$D$13,Supuestos!$C$19-1)*Supuestos!C$46*Supuestos!$C$5+INDEX(Supuestos!$B$14:$D$14,Supuestos!$C$19-1)*Supuestos!C$46*Supuestos!$C$6+INDEX(Supuestos!$B$15:$D$15,Supuestos!$C$19-1)*Supuestos!C$46*Supuestos!$C$7+'Cartera recurrente'!C7*Supuestos!$C$8+'Cartera recurrente'!C13*Supuestos!$C$9)*(1+Supuestos!$B$37) | D22: =-(INDEX(Supuestos!$B$13:$D$13,Supuestos!$C$19-1)*Supuestos!D$46*Supuestos!$C$5+INDEX(Supuestos!$B$14:$D$14,Supuestos!$C$19-1)*Supuestos!D$46*Supuestos!$C$6+INDEX(Supuestos!$B$15:$D$15,Supuestos!$C$19-1)*Supuestos!D$46*Supuestos!$C$7+'Cartera recurrente'!D7*Supuestos!$C$8+'Cartera recurrente'!D13*Supuestos!$C$9)*(1+Supuestos!$B$37) | E22: =-(INDEX(Supuestos!$B$13:$D$13,Supuestos!$C$19-1)*Supuestos!E$46*Supuestos!$C$5+INDEX(Supuestos!$B$14:$D$14,Supuestos!$C$19-1)*Supuestos!E$46*Supuestos!$C$6+INDEX(Supuestos!$B$15:$D$15,Supuestos!$C$19-1)*Supuestos!E$46*Supuestos!$C$7+'Cartera recurrente'!E7*Supuestos!$C$8+'Cartera recurrente'!E13*Supuestos!$C$9)*(1+Supuestos!$B$37) | F22: =-(INDEX(Supuestos!$B$13:$D$13,Supuestos!$C$19-1)*Supuestos!F$46*Supuestos!$C$5+INDEX(Supuestos!$B$14:$D$14,Supuestos!$C$19-1)*Supuestos!F$46*Supuestos!$C$6+INDEX(Supuestos!$B$15:$D$15,Supuestos!$C$19-1)*Supuestos!F$46*Supuestos!$C$7+'Cartera recurrente'!F7*Supuestos!$C$8+'Cartera recurrente'!F13*Supuestos!$C$9)*(1+Supuestos!$B$37) | G22: =-(INDEX(Supuestos!$B$13:$D$13,Supuestos!$C$19-1)*Supuestos!G$46*Supuestos!$C$5+INDEX(Supuestos!$B$14:$D$14,Supuestos!$C$19-1)*Supuestos!G$46*Supuestos!$C$6+INDEX(Supuestos!$B$15:$D$15,Supuestos!$C$19-1)*Supuestos!G$46*Supuestos!$C$7+'Cartera recurrente'!G7*Supuestos!$C$8+'Cartera recurrente'!G13*Supuestos!$C$9)*(1+Supuestos!$B$37) | H22: =-(INDEX(Supuestos!$B$13:$D$13,Supuestos!$C$19-1)*Supuestos!H$46*Supuestos!$C$5+INDEX(Supuestos!$B$14:$D$14,Supuestos!$C$19-1)*Supuestos!H$46*Supuestos!$C$6+INDEX(Supuestos!$B$15:$D$15,Supuestos!$C$19-1)*Supuestos!H$46*Supuestos!$C$7+'Cartera recurrente'!H7*Supuestos!$C$8+'Cartera recurrente'!H13*Supuestos!$C$9)*(1+Supuestos!$B$37) | I22: =-(INDEX(Supuestos!$B$13:$D$13,Supuestos!$C$19-1)*Supuestos!I$46*Supuestos!$C$5+INDEX(Supuestos!$B$14:$D$14,Supuestos!$C$19-1)*Supuestos!I$46*Supuestos!$C$6+INDEX(Supuestos!$B$15:$D$15,Supuestos!$C$19-1)*Supuestos!I$46*Supuestos!$C$7+'Cartera recurrente'!I7*Supuestos!$C$8+'Cartera recurrente'!I13*Supuestos!$C$9)*(1+Supuestos!$B$37) | ... M22: =-(INDEX(Supuestos!$B$13:$D$13,Supuestos!$C$19-1)*Supuestos!M$46*Supuestos!$C$5+INDEX(Supuestos!$B$14:$D$14,Supuestos!$C$19-1)*Supuestos!M$46*Supuestos!$C$6+INDEX(Supuestos!$B$15:$D$15,Supuestos!$C$19-1)*Supuestos!M$46*Supuestos!$C$7+'Cartera recurrente'!M7*Supuestos!$C$8+'Cartera recurrente'!M13*Supuestos!$C$9)*(1+Supuestos!$B$37) | N22: =SUM(B22:M22)
A23: Gastos fijos | B23: =-Supuestos!$B$30*(1+Supuestos!$B$37) | C23: =-Supuestos!$B$30*(1+Supuestos!$B$37) | D23: =-Supuestos!$B$30*(1+Supuestos!$B$37) | E23: =-Supuestos!$B$30*(1+Supuestos!$B$37) | F23: =-Supuestos!$B$30*(1+Supuestos!$B$37) | G23: =-Supuestos!$B$30*(1+Supuestos!$B$37) | H23: =-Supuestos!$B$30*(1+Supuestos!$B$37) | I23: =-Supuestos!$B$30*(1+Supuestos!$B$37) | ... M23: =-Supuestos!$B$30*(1+Supuestos!$B$37) | N23: =SUM(B23:M23)
A24: Seguro de RC profesional | B24: =-Supuestos!$B$31 | C24: =0 | D24: =0 | E24: =0 | F24: =0 | G24: =0 | H24: =0 | I24: =0 | J24: =0 | ... M24: =0 | N24: =SUM(B24:M24)
A25: Tu retirada | B25: =-Supuestos!$B$40 | C25: =-Supuestos!$B$40 | D25: =-Supuestos!$B$40 | E25: =-Supuestos!$B$40 | F25: =-Supuestos!$B$40 | G25: =-Supuestos!$B$40 | H25: =-Supuestos!$B$40 | I25: =-Supuestos!$B$40 | ... M25: =-Supuestos!$B$40 | N25: =SUM(B25:M25)
A26: Liquidación de IVA (trimestral) | B26: =0 | C26: =0 | D26: =0 | E26: =-MAX(0,SUM(B17:D17)+SUM(B22:D22)*Supuestos!$B$37/(1+Supuestos!$B$37)+SUM(B23:D23)*Supuestos!$B$37/(1+Supuestos!$B$37)) | F26: =0 | G26: =0 | H26: =-MAX(0,SUM(E17:G17)+SUM(E22:G22)*Supuestos!$B$37/(1+Supuestos!$B$37)+SUM(E23:G23)*Supuestos!$B$37/(1+Supuestos!$B$37)) | I26: =0 | J26: =0 | K26: =-MAX(0,SUM(H17:J17)+SUM(H22:J22)*Supuestos!$B$37/(1+Supuestos!$B$37)+SUM(H23:J23)*Supuestos!$B$37/(1+Supuestos!$B$37)) | L26: =0 | M26: =0 | N26: =SUM(B26:M26)
A27: TOTAL PAGOS | B27: =SUM(B22:B26) | C27: =SUM(C22:C26) | D27: =SUM(D22:D26) | E27: =SUM(E22:E26) | F27: =SUM(F22:F26) | G27: =SUM(G22:G26) | H27: =SUM(H22:H26) | I27: =SUM(I22:I26) | ... M27: =SUM(M22:M26) | N27: =SUM(B27:M27)
A29: CAJA
A30: Saldo inicial del mes | B30: =Supuestos!$B$34 | C30: =B32 | D30: =C32 | E30: =D32 | F30: =E32 | G30: =F32 | H30: =G32 | I30: =H32 | J30: =I32 | ... M30: =L32
A31: Movimiento del mes | B31: =B19+B27 | C31: =C19+C27 | D31: =D19+D27 | E31: =E19+E27 | F31: =F19+F27 | G31: =G19+G27 | H31: =H19+H27 | I31: =I19+I27 | ... M31: =M19+M27 | N31: =SUM(B31:M31)
A32: SALDO FINAL DEL MES | B32: =B30+B31 | C32: =C30+C31 | D32: =D30+D31 | E32: =E30+E31 | F32: =F30+F31 | G32: =G30+G31 | H32: =H30+H31 | I32: =I30+I31 | ... M32: =M30+M31 | N32: =M32
A34: ⚠ ¿NECESITAS DINERO ESTE MES? | B34: =IF(B32<0,"FALTA","ok") | C34: =IF(C32<0,"FALTA","ok") | D34: =IF(D32<0,"FALTA","ok") | E34: =IF(E32<0,"FALTA","ok") | F34: =IF(F32<0,"FALTA","ok") | G34: =IF(G32<0,"FALTA","ok") | H34: =IF(H32<0,"FALTA","ok") | I34: =IF(I32<0,"FALTA","ok") | ... M34: =IF(M32<0,"FALTA","ok")
A36: Caja mínima del año | B36: =MIN(B32:M32)
A37: Colchón que necesitarías para no entrar en negativo | B37: =IF(B36>=0,0,-B36)
A38: Meses en negativo | B38: =COUNTIF(B32:M32,"<0")

Sheet Cartera recurrente
A1: CARTERA RECURRENTE — altas, bajas y clientes activos
B3: Mes 1 | C3: Mes 2 | D3: Mes 3 | E3: Mes 4 | F3: Mes 5 | G3: Mes 6 | H3: Mes 7 | I3: Mes 8 | J3: Mes 9 | K3: Mes 10 | L3: Mes 11 | M3: Mes 12
A4: MANTENIMIENTO (60 €/mes)
A5: Altas del mes | B5: =INDEX(Supuestos!$B$16:$D$16,Supuestos!$C$19-1)*Supuestos!B$46*12 | C5: =INDEX(Supuestos!$B$16:$D$16,Supuestos!$C$19-1)*Supuestos!C$46*12 | D5: =INDEX(Supuestos!$B$16:$D$16,Supuestos!$C$19-1)*Supuestos!D$46*12 | E5: =INDEX(Supuestos!$B$16:$D$16,Supuestos!$C$19-1)*Supuestos!E$46*12 | F5: =INDEX(Supuestos!$B$16:$D$16,Supuestos!$C$19-1)*Supuestos!F$46*12 | G5: =INDEX(Supuestos!$B$16:$D$16,Supuestos!$C$19-1)*Supuestos!G$46*12 | H5: =INDEX(Supuestos!$B$16:$D$16,Supuestos!$C$19-1)*Supuestos!H$46*12 | I5: =INDEX(Supuestos!$B$16:$D$16,Supuestos!$C$19-1)*Supuestos!I$46*12 | ... M5: =INDEX(Supuestos!$B$16:$D$16,Supuestos!$C$19-1)*Supuestos!M$46*12
A6: Bajas del mes | B6: =0 | C6: =-B7*Supuestos!$B$39 | D6: =-C7*Supuestos!$B$39 | E6: =-D7*Supuestos!$B$39 | F6: =-E7*Supuestos!$B$39 | G6: =-F7*Supuestos!$B$39 | H6: =-G7*Supuestos!$B$39 | I6: =-H7*Supuestos!$B$39 | J6: =-I7*Supuestos!$B$39 | ... M6: =-L7*Supuestos!$B$39
A7: CLIENTES ACTIVOS | B7: =B5+B6 | C7: =B7+C5+C6 | D7: =C7+D5+D6 | E7: =D7+E5+E6 | F7: =E7+F5+F6 | G7: =F7+G5+G6 | H7: =G7+H5+H6 | I7: =H7+I5+I6 | J7: =I7+J5+J6 | ... M7: =L7+M5+M6
A10: SEO LOCAL (250 €/mes)
A11: Altas del mes | B11: =INDEX(Supuestos!$B$17:$D$17,Supuestos!$C$19-1)*Supuestos!B$46*12 | C11: =INDEX(Supuestos!$B$17:$D$17,Supuestos!$C$19-1)*Supuestos!C$46*12 | D11: =INDEX(Supuestos!$B$17:$D$17,Supuestos!$C$19-1)*Supuestos!D$46*12 | E11: =INDEX(Supuestos!$B$17:$D$17,Supuestos!$C$19-1)*Supuestos!E$46*12 | F11: =INDEX(Supuestos!$B$17:$D$17,Supuestos!$C$19-1)*Supuestos!F$46*12 | G11: =INDEX(Supuestos!$B$17:$D$17,Supuestos!$C$19-1)*Supuestos!G$46*12 | H11: =INDEX(Supuestos!$B$17:$D$17,Supuestos!$C$19-1)*Supuestos!H$46*12 | I11: =INDEX(Supuestos!$B$17:$D$17,Supuestos!$C$19-1)*Supuestos!I$46*12 | ... M11: =INDEX(Supuestos!$B$17:$D$17,Supuestos!$C$19-1)*Supuestos!M$46*12
A12: Bajas del mes | B12: =0 | C12: =-B13*Supuestos!$B$39 | D12: =-C13*Supuestos!$B$39 | E12: =-D13*Supuestos!$B$39 | F12: =-E13*Supuestos!$B$39 | G12: =-F13*Supuestos!$B$39 | H12: =-G13*Supuestos!$B$39 | I12: =-H13*Supuestos!$B$39 | J12: =-I13*Supuestos!$B$39 | ... M12: =-L13*Supuestos!$B$39
A13: CLIENTES ACTIVOS | B13: =B11+B12 | C13: =B13+C11+C12 | D13: =C13+D11+D12 | E13: =D13+E11+E12 | F13: =E13+F11+F12 | G13: =F13+G11+G12 | H13: =G13+H11+H12 | I13: =H13+I11+I12 | J13: =I13+J11+J12 | ... M13: =L13+M11+M12
A16: Ingreso recurrente del mes 12 | B16: =M7*Supuestos!$B$8+M13*Supuestos!$B$9
A17: Peso del recurrente sobre las ventas del año | B17: =IF('Rampa mensual'!N10=0,0,SUM('Rampa mensual'!N8:N9)/'Rampa mensual'!N10)
A19: Cada cliente de mantenimiento vale, a 12 meses: | B19: =Supuestos!$B$8*12
A20: Cada cliente de SEO vale, a 12 meses: | B20: =Supuestos!$B$9*12

Sheet Escenarios
A1: LOS TRES ESCENARIOS, LADO A LADO
A3: Cambia "ESCENARIO ACTIVO" en la hoja Supuestos y apunta aquí el resultado. El libro recalcula solo, pero esta tabla es manual a propósito: sirve para comparar los tres de un vistazo.
B5: Pesimista | C5: Previsto | D5: Optimista
A6: Ventas del año (sin IVA) | F6: ← Rellena a mano tras probar cada escenario
A7: Caja mínima del año
A8: Meses en negativo
A9: Colchón necesario
A10: Clientes recurrentes al mes 12
A11: Peso del ingreso recurrente

Sheet Calendario fiscal
A1: CALENDARIO FISCAL — qué se presenta y cuándo
A3: Cuándo | B3: Modelo | C3: Qué es | D3: Periodo que declara | E3: Notas
A4: Antes de empezar | B4: 036/037 | C4: Alta censal en Hacienda: epígrafes de IAE, IVA e IRPF | D4: Una sola vez | E4: Declara aquí los METROS AFECTOS de tu casa o no podrás deducir suministros
A5: Antes de empezar | B5: TA.0521 | C5: Alta en el RETA (Seguridad Social) | D5: Una sola vez | E5: Hasta 60 días antes del inicio. Pide la TARIFA PLANA de 80 €/mes
A6: 1-20 abril | B6: 303 | C6: IVA del 1er trimestre | D6: Ene-Mar | E6: Siempre, aunque salga a cero
A7: 1-20 abril | B7: 130 | C7: Pago fraccionado del IRPF (20%) | D7: Ene-Mar | E7: SOLO si tu epígrafe es empresarial. Si es profesional y te retienen, no lo presentas
A8: 1-20 abril | B8: 111 | C8: Retenciones a profesionales | D8: Ene-Mar | E8: Solo si pagas facturas con retención
A9: 1-20 julio | B9: 303 / 130 / 111 | C9: Mismo trío | D9: Abr-Jun
A10: 1-20 octubre | B10: 303 / 130 / 111 | C10: Mismo trío | D10: Jul-Sep
A11: 1-30 enero | B11: 303 / 130 / 111 | C11: Mismo trío del 4º trimestre | D11: Oct-Dic | E11: Ojo: el plazo es hasta el día 30
A12: 1-30 enero | B12: 390 | C12: Resumen anual del IVA | D12: Todo el año
A13: 1-31 enero | B13: 190 | C13: Resumen anual de retenciones | D13: Todo el año | E13: Solo si presentaste el 111
A14: Febrero | B14: 347 | C14: Operaciones con terceros > 3.005,06 € | D14: Año anterior
A15: Abril-junio | B15: 100 | C15: Declaración de la Renta | D15: Año anterior | E15: Aquí aplicas la REDUCCIÓN DEL 20% POR INICIO DE ACTIVIDAD
A16: Mes 10 de actividad | B16: — | C16: Revisar si puedes prorrogar la tarifa plana | D16: — | E16: Si tu rendimiento neto va por debajo del SMI (1.184 €/mes), SOLICÍTALA. No es automática
A17: Mes 12 | B17: — | C17: Fin de la tarifa plana | D17: — | E17: La cuota pasa de 80 a unos 330 €/mes. Ten apartados 3.000 €
A18: 1 julio 2027 | B18: Verifactu | C18: Factura verificable con software homologado | D18: — | E18: Obligatorio para autónomos desde esa fecha. Elige ya un programa adaptado
